<?xml version="1.0" encoding="utf-8"?>
<TextureAtlas imagePath="gfcute.png">
	<!-- Created with Adobe Animate version 22.0.5.191 -->
	<!-- http://www.adobe.com/products/animate.html -->
	<SubTexture name="GF Down0000" x="5" y="5" width="327" height="447" frameX="0" frameY="-15" frameWidth="327" frameHeight="463"/>
	<SubTexture name="GF Down0001" x="5" y="5" width="327" height="447" frameX="0" frameY="-15" frameWidth="327" frameHeight="463"/>
	<SubTexture name="GF Down0002" x="337" y="5" width="323" height="457" frameX="-3" frameY="-6" frameWidth="327" frameHeight="463"/>
	<SubTexture name="GF Down0003" x="337" y="5" width="323" height="457" frameX="-3" frameY="-6" frameWidth="327" frameHeight="463"/>
	<SubTexture name="GF Down0004" x="665" y="5" width="325" height="463" frameX="-1" frameY="0" frameWidth="327" frameHeight="463"/>
	<SubTexture name="GF Down0005" x="665" y="5" width="325" height="463" frameX="-1" frameY="0" frameWidth="327" frameHeight="463"/>
	<SubTexture name="GF Down0006" x="665" y="5" width="325" height="463" frameX="-1" frameY="0" frameWidth="327" frameHeight="463"/>
	<SubTexture name="GF Down0007" x="665" y="5" width="325" height="463" frameX="-1" frameY="0" frameWidth="327" frameHeight="463"/>
	<SubTexture name="GF Down0008" x="665" y="5" width="325" height="463" frameX="-1" frameY="0" frameWidth="327" frameHeight="463"/>
	<SubTexture name="GF Down0009" x="665" y="5" width="325" height="463" frameX="-1" frameY="0" frameWidth="327" frameHeight="463"/>
	<SubTexture name="GF Down0010" x="665" y="5" width="325" height="463" frameX="-1" frameY="0" frameWidth="327" frameHeight="463"/>
	<SubTexture name="GF Down0011" x="665" y="5" width="325" height="463" frameX="-1" frameY="0" frameWidth="327" frameHeight="463"/>
	<SubTexture name="GF Down0012" x="665" y="5" width="325" height="463" frameX="-1" frameY="0" frameWidth="327" frameHeight="463"/>
	<SubTexture name="GF Down0013" x="665" y="5" width="325" height="463" frameX="-1" frameY="0" frameWidth="327" frameHeight="463"/>
	<SubTexture name="GF Down0014" x="665" y="5" width="325" height="463" frameX="-1" frameY="0" frameWidth="327" frameHeight="463"/>
	<SubTexture name="GF Idle0000" x="995" y="5" width="324" height="473" frameX="0" frameY="-20" frameWidth="356" frameHeight="493"/>
	<SubTexture name="GF Idle0001" x="995" y="5" width="324" height="473" frameX="0" frameY="-20" frameWidth="356" frameHeight="493"/>
	<SubTexture name="GF Idle0002" x="1324" y="5" width="326" height="474" frameX="0" frameY="-19" frameWidth="356" frameHeight="493"/>
	<SubTexture name="GF Idle0003" x="1324" y="5" width="326" height="474" frameX="0" frameY="-19" frameWidth="356" frameHeight="493"/>
	<SubTexture name="GF Idle0004" x="1655" y="5" width="319" height="477" frameX="-10" frameY="-16" frameWidth="356" frameHeight="493"/>
	<SubTexture name="GF Idle0005" x="1655" y="5" width="319" height="477" frameX="-10" frameY="-16" frameWidth="356" frameHeight="493"/>
	<SubTexture name="GF Idle0006" x="1979" y="5" width="316" height="476" frameX="-14" frameY="-17" frameWidth="356" frameHeight="493"/>
	<SubTexture name="GF Idle0007" x="1979" y="5" width="316" height="476" frameX="-14" frameY="-17" frameWidth="356" frameHeight="493"/>
	<SubTexture name="GF Idle0008" x="1979" y="5" width="316" height="476" frameX="-14" frameY="-17" frameWidth="356" frameHeight="493"/>
	<SubTexture name="GF Idle0009" x="1979" y="5" width="316" height="476" frameX="-14" frameY="-17" frameWidth="356" frameHeight="493"/>
	<SubTexture name="GF Idle0010" x="1979" y="5" width="316" height="476" frameX="-14" frameY="-17" frameWidth="356" frameHeight="493"/>
	<SubTexture name="GF Idle0011" x="1979" y="5" width="316" height="476" frameX="-14" frameY="-17" frameWidth="356" frameHeight="493"/>
	<SubTexture name="GF Idle0012" x="5" y="487" width="320" height="486" frameX="-17" frameY="-7" frameWidth="356" frameHeight="493"/>
	<SubTexture name="GF Idle0013" x="5" y="487" width="320" height="486" frameX="-17" frameY="-7" frameWidth="356" frameHeight="493"/>
	<SubTexture name="GF Idle0014" x="330" y="487" width="336" height="485" frameX="-20" frameY="-8" frameWidth="356" frameHeight="493"/>
	<SubTexture name="GF Idle0015" x="330" y="487" width="336" height="485" frameX="-20" frameY="-8" frameWidth="356" frameHeight="493"/>
	<SubTexture name="GF Idle0016" x="671" y="487" width="331" height="493" frameX="-17" frameY="0" frameWidth="356" frameHeight="493"/>
	<SubTexture name="GF Idle0017" x="671" y="487" width="331" height="493" frameX="-17" frameY="0" frameWidth="356" frameHeight="493"/>
	<SubTexture name="GF Idle0018" x="5" y="487" width="320" height="486" frameX="-17" frameY="-7" frameWidth="356" frameHeight="493"/>
	<SubTexture name="GF Idle0019" x="5" y="487" width="320" height="486" frameX="-17" frameY="-7" frameWidth="356" frameHeight="493"/>
	<SubTexture name="GF Idle0020" x="1007" y="487" width="313" height="475" frameX="-15" frameY="-18" frameWidth="356" frameHeight="493"/>
	<SubTexture name="GF Idle0021" x="1007" y="487" width="313" height="475" frameX="-15" frameY="-18" frameWidth="356" frameHeight="493"/>
	<SubTexture name="GF Idle0022" x="1007" y="487" width="313" height="475" frameX="-15" frameY="-18" frameWidth="356" frameHeight="493"/>
	<SubTexture name="GF Idle0023" x="1007" y="487" width="313" height="475" frameX="-15" frameY="-18" frameWidth="356" frameHeight="493"/>
	<SubTexture name="GF Idle0024" x="1007" y="487" width="313" height="475" frameX="-15" frameY="-18" frameWidth="356" frameHeight="493"/>
	<SubTexture name="GF Idle0025" x="1007" y="487" width="313" height="475" frameX="-15" frameY="-18" frameWidth="356" frameHeight="493"/>
	<SubTexture name="GF Idle0026" x="1655" y="5" width="319" height="477" frameX="-10" frameY="-16" frameWidth="356" frameHeight="493"/>
	<SubTexture name="GF Idle0027" x="1655" y="5" width="319" height="477" frameX="-10" frameY="-16" frameWidth="356" frameHeight="493"/>
	<SubTexture name="GF Left0000" x="1325" y="487" width="387" height="483" frameX="0" frameY="0" frameWidth="396" frameHeight="483"/>
	<SubTexture name="GF Left0001" x="1325" y="487" width="387" height="483" frameX="0" frameY="0" frameWidth="396" frameHeight="483"/>
	<SubTexture name="GF Left0002" x="1717" y="487" width="395" height="476" frameX="-1" frameY="-7" frameWidth="396" frameHeight="483"/>
	<SubTexture name="GF Left0003" x="1717" y="487" width="395" height="476" frameX="-1" frameY="-7" frameWidth="396" frameHeight="483"/>
	<SubTexture name="GF Left0004" x="2117" y="487" width="395" height="474" frameX="-1" frameY="-9" frameWidth="396" frameHeight="483"/>
	<SubTexture name="GF Left0005" x="2117" y="487" width="395" height="474" frameX="-1" frameY="-9" frameWidth="396" frameHeight="483"/>
	<SubTexture name="GF Left0006" x="2117" y="487" width="395" height="474" frameX="-1" frameY="-9" frameWidth="396" frameHeight="483"/>
	<SubTexture name="GF Left0007" x="2117" y="487" width="395" height="474" frameX="-1" frameY="-9" frameWidth="396" frameHeight="483"/>
	<SubTexture name="GF Left0008" x="2117" y="487" width="395" height="474" frameX="-1" frameY="-9" frameWidth="396" frameHeight="483"/>
	<SubTexture name="GF Left0009" x="2117" y="487" width="395" height="474" frameX="-1" frameY="-9" frameWidth="396" frameHeight="483"/>
	<SubTexture name="GF Left0010" x="2117" y="487" width="395" height="474" frameX="-1" frameY="-9" frameWidth="396" frameHeight="483"/>
	<SubTexture name="GF Left0011" x="2117" y="487" width="395" height="474" frameX="-1" frameY="-9" frameWidth="396" frameHeight="483"/>
	<SubTexture name="GF Left0012" x="2117" y="487" width="395" height="474" frameX="-1" frameY="-9" frameWidth="396" frameHeight="483"/>
	<SubTexture name="GF Left0013" x="2117" y="487" width="395" height="474" frameX="-1" frameY="-9" frameWidth="396" frameHeight="483"/>
	<SubTexture name="GF Left0014" x="2117" y="487" width="395" height="474" frameX="-1" frameY="-9" frameWidth="396" frameHeight="483"/>
	<SubTexture name="GF Right0000" x="5" y="985" width="318" height="480" frameX="-16" frameY="-4" frameWidth="334" frameHeight="484"/>
	<SubTexture name="GF Right0001" x="5" y="985" width="318" height="480" frameX="-16" frameY="-4" frameWidth="334" frameHeight="484"/>
	<SubTexture name="GF Right0002" x="328" y="985" width="316" height="484" frameX="-10" frameY="0" frameWidth="334" frameHeight="484"/>
	<SubTexture name="GF Right0003" x="328" y="985" width="316" height="484" frameX="-10" frameY="0" frameWidth="334" frameHeight="484"/>
	<SubTexture name="GF Right0004" x="649" y="985" width="332" height="476" frameX="0" frameY="-8" frameWidth="334" frameHeight="484"/>
	<SubTexture name="GF Right0005" x="649" y="985" width="332" height="476" frameX="0" frameY="-8" frameWidth="334" frameHeight="484"/>
	<SubTexture name="GF Right0006" x="649" y="985" width="332" height="476" frameX="0" frameY="-8" frameWidth="334" frameHeight="484"/>
	<SubTexture name="GF Right0007" x="649" y="985" width="332" height="476" frameX="0" frameY="-8" frameWidth="334" frameHeight="484"/>
	<SubTexture name="GF Right0008" x="649" y="985" width="332" height="476" frameX="0" frameY="-8" frameWidth="334" frameHeight="484"/>
	<SubTexture name="GF Right0009" x="649" y="985" width="332" height="476" frameX="0" frameY="-8" frameWidth="334" frameHeight="484"/>
	<SubTexture name="GF Right0010" x="649" y="985" width="332" height="476" frameX="0" frameY="-8" frameWidth="334" frameHeight="484"/>
	<SubTexture name="GF Right0011" x="649" y="985" width="332" height="476" frameX="0" frameY="-8" frameWidth="334" frameHeight="484"/>
	<SubTexture name="GF Right0012" x="649" y="985" width="332" height="476" frameX="0" frameY="-8" frameWidth="334" frameHeight="484"/>
	<SubTexture name="GF Right0013" x="649" y="985" width="332" height="476" frameX="0" frameY="-8" frameWidth="334" frameHeight="484"/>
	<SubTexture name="GF Right0014" x="649" y="985" width="332" height="476" frameX="0" frameY="-8" frameWidth="334" frameHeight="484"/>
	<SubTexture name="GF Up0000" x="986" y="985" width="345" height="509" frameX="-3" frameY="0" frameWidth="359" frameHeight="509"/>
	<SubTexture name="GF Up0001" x="986" y="985" width="345" height="509" frameX="-3" frameY="0" frameWidth="359" frameHeight="509"/>
	<SubTexture name="GF Up0002" x="1336" y="985" width="346" height="499" frameX="0" frameY="-9" frameWidth="359" frameHeight="509"/>
	<SubTexture name="GF Up0003" x="1336" y="985" width="346" height="499" frameX="0" frameY="-9" frameWidth="359" frameHeight="509"/>
	<SubTexture name="GF Up0004" x="1687" y="985" width="358" height="495" frameX="-1" frameY="-13" frameWidth="359" frameHeight="509"/>
	<SubTexture name="GF Up0005" x="1687" y="985" width="358" height="495" frameX="-1" frameY="-13" frameWidth="359" frameHeight="509"/>
	<SubTexture name="GF Up0006" x="1687" y="985" width="358" height="495" frameX="-1" frameY="-13" frameWidth="359" frameHeight="509"/>
	<SubTexture name="GF Up0007" x="1687" y="985" width="358" height="495" frameX="-1" frameY="-13" frameWidth="359" frameHeight="509"/>
	<SubTexture name="GF Up0008" x="1687" y="985" width="358" height="495" frameX="-1" frameY="-13" frameWidth="359" frameHeight="509"/>
	<SubTexture name="GF Up0009" x="1687" y="985" width="358" height="495" frameX="-1" frameY="-13" frameWidth="359" frameHeight="509"/>
	<SubTexture name="GF Up0010" x="1687" y="985" width="358" height="495" frameX="-1" frameY="-13" frameWidth="359" frameHeight="509"/>
	<SubTexture name="GF Up0011" x="1687" y="985" width="358" height="495" frameX="-1" frameY="-13" frameWidth="359" frameHeight="509"/>
	<SubTexture name="GF Up0012" x="1687" y="985" width="358" height="495" frameX="-1" frameY="-13" frameWidth="359" frameHeight="509"/>
	<SubTexture name="GF Up0013" x="1687" y="985" width="358" height="495" frameX="-1" frameY="-13" frameWidth="359" frameHeight="509"/>
	<SubTexture name="GF Up0014" x="1687" y="985" width="358" height="495" frameX="-1" frameY="-13" frameWidth="359" frameHeight="509"/>
	<SubTexture name="MISS GF Down0000" x="2050" y="985" width="385" height="438" frameX="0" frameY="-6" frameWidth="385" frameHeight="444"/>
	<SubTexture name="MISS GF Down0001" x="2050" y="985" width="385" height="438" frameX="0" frameY="-6" frameWidth="385" frameHeight="444"/>
	<SubTexture name="MISS GF Down0002" x="5" y="1499" width="378" height="444" frameX="-3" frameY="0" frameWidth="385" frameHeight="444"/>
	<SubTexture name="MISS GF Down0003" x="5" y="1499" width="378" height="444" frameX="-3" frameY="0" frameWidth="385" frameHeight="444"/>
	<SubTexture name="MISS GF Down0004" x="5" y="1499" width="378" height="444" frameX="-3" frameY="0" frameWidth="385" frameHeight="444"/>
	<SubTexture name="MISS GF Down0005" x="5" y="1499" width="378" height="444" frameX="-3" frameY="0" frameWidth="385" frameHeight="444"/>
	<SubTexture name="MISS GF Down0006" x="5" y="1499" width="378" height="444" frameX="-3" frameY="0" frameWidth="385" frameHeight="444"/>
	<SubTexture name="MISS GF Down0007" x="5" y="1499" width="378" height="444" frameX="-3" frameY="0" frameWidth="385" frameHeight="444"/>
	<SubTexture name="MISS GF Down0008" x="5" y="1499" width="378" height="444" frameX="-3" frameY="0" frameWidth="385" frameHeight="444"/>
	<SubTexture name="MISS GF Down0009" x="5" y="1499" width="378" height="444" frameX="-3" frameY="0" frameWidth="385" frameHeight="444"/>
	<SubTexture name="MISS GF Down0010" x="5" y="1499" width="378" height="444" frameX="-3" frameY="0" frameWidth="385" frameHeight="444"/>
	<SubTexture name="MISS GF Down0011" x="5" y="1499" width="378" height="444" frameX="-3" frameY="0" frameWidth="385" frameHeight="444"/>
	<SubTexture name="MISS GF Down0012" x="5" y="1499" width="378" height="444" frameX="-3" frameY="0" frameWidth="385" frameHeight="444"/>
	<SubTexture name="MISS GF Down0013" x="5" y="1499" width="378" height="444" frameX="-3" frameY="0" frameWidth="385" frameHeight="444"/>
	<SubTexture name="MISS GF Down0014" x="5" y="1499" width="378" height="444" frameX="-3" frameY="0" frameWidth="385" frameHeight="444"/>
	<SubTexture name="MISS GF Left0000" x="388" y="1499" width="389" height="469" frameX="0" frameY="0" frameWidth="389" frameHeight="470"/>
	<SubTexture name="MISS GF Left0001" x="388" y="1499" width="389" height="469" frameX="0" frameY="0" frameWidth="389" frameHeight="470"/>
	<SubTexture name="MISS GF Left0002" x="782" y="1499" width="378" height="465" frameX="-10" frameY="-5" frameWidth="389" frameHeight="470"/>
	<SubTexture name="MISS GF Left0003" x="782" y="1499" width="378" height="465" frameX="-10" frameY="-5" frameWidth="389" frameHeight="470"/>
	<SubTexture name="MISS GF Left0004" x="782" y="1499" width="378" height="465" frameX="-10" frameY="-5" frameWidth="389" frameHeight="470"/>
	<SubTexture name="MISS GF Left0005" x="782" y="1499" width="378" height="465" frameX="-10" frameY="-5" frameWidth="389" frameHeight="470"/>
	<SubTexture name="MISS GF Left0006" x="782" y="1499" width="378" height="465" frameX="-10" frameY="-5" frameWidth="389" frameHeight="470"/>
	<SubTexture name="MISS GF Left0007" x="782" y="1499" width="378" height="465" frameX="-10" frameY="-5" frameWidth="389" frameHeight="470"/>
	<SubTexture name="MISS GF Left0008" x="782" y="1499" width="378" height="465" frameX="-10" frameY="-5" frameWidth="389" frameHeight="470"/>
	<SubTexture name="MISS GF Left0009" x="782" y="1499" width="378" height="465" frameX="-10" frameY="-5" frameWidth="389" frameHeight="470"/>
	<SubTexture name="MISS GF Left0010" x="782" y="1499" width="378" height="465" frameX="-10" frameY="-5" frameWidth="389" frameHeight="470"/>
	<SubTexture name="MISS GF Left0011" x="782" y="1499" width="378" height="465" frameX="-10" frameY="-5" frameWidth="389" frameHeight="470"/>
	<SubTexture name="MISS GF Left0012" x="782" y="1499" width="378" height="465" frameX="-10" frameY="-5" frameWidth="389" frameHeight="470"/>
	<SubTexture name="MISS GF Left0013" x="782" y="1499" width="378" height="465" frameX="-10" frameY="-5" frameWidth="389" frameHeight="470"/>
	<SubTexture name="MISS GF Left0014" x="782" y="1499" width="378" height="465" frameX="-10" frameY="-5" frameWidth="389" frameHeight="470"/>
	<SubTexture name="MISS GF Right0000" x="1165" y="1499" width="335" height="480"/>
	<SubTexture name="MISS GF Right0001" x="1165" y="1499" width="335" height="480"/>
	<SubTexture name="MISS GF Right0002" x="1505" y="1499" width="311" height="470" frameX="-1" frameY="-9" frameWidth="335" frameHeight="480"/>
	<SubTexture name="MISS GF Right0003" x="1505" y="1499" width="311" height="470" frameX="-1" frameY="-9" frameWidth="335" frameHeight="480"/>
	<SubTexture name="MISS GF Right0004" x="1505" y="1499" width="311" height="470" frameX="-1" frameY="-9" frameWidth="335" frameHeight="480"/>
	<SubTexture name="MISS GF Right0005" x="1505" y="1499" width="311" height="470" frameX="-1" frameY="-9" frameWidth="335" frameHeight="480"/>
	<SubTexture name="MISS GF Right0006" x="1505" y="1499" width="311" height="470" frameX="-1" frameY="-9" frameWidth="335" frameHeight="480"/>
	<SubTexture name="MISS GF Right0007" x="1505" y="1499" width="311" height="470" frameX="-1" frameY="-9" frameWidth="335" frameHeight="480"/>
	<SubTexture name="MISS GF Right0008" x="1505" y="1499" width="311" height="470" frameX="-1" frameY="-9" frameWidth="335" frameHeight="480"/>
	<SubTexture name="MISS GF Right0009" x="1505" y="1499" width="311" height="470" frameX="-1" frameY="-9" frameWidth="335" frameHeight="480"/>
	<SubTexture name="MISS GF Right0010" x="1505" y="1499" width="311" height="470" frameX="-1" frameY="-9" frameWidth="335" frameHeight="480"/>
	<SubTexture name="MISS GF Right0011" x="1505" y="1499" width="311" height="470" frameX="-1" frameY="-9" frameWidth="335" frameHeight="480"/>
	<SubTexture name="MISS GF Right0012" x="1505" y="1499" width="311" height="470" frameX="-1" frameY="-9" frameWidth="335" frameHeight="480"/>
	<SubTexture name="MISS GF Right0013" x="1505" y="1499" width="311" height="470" frameX="-1" frameY="-9" frameWidth="335" frameHeight="480"/>
	<SubTexture name="MISS GF Right0014" x="1505" y="1499" width="311" height="470" frameX="-1" frameY="-9" frameWidth="335" frameHeight="480"/>
	<SubTexture name="MISS GF Up0000" x="1821" y="1499" width="348" height="497" frameX="-3" frameY="0" frameWidth="353" frameHeight="497"/>
	<SubTexture name="MISS GF Up0001" x="1821" y="1499" width="348" height="497" frameX="-3" frameY="0" frameWidth="353" frameHeight="497"/>
	<SubTexture name="MISS GF Up0002" x="2174" y="1499" width="353" height="497"/>
	<SubTexture name="MISS GF Up0003" x="2174" y="1499" width="353" height="497"/>
	<SubTexture name="MISS GF Up0004" x="2174" y="1499" width="353" height="497"/>
	<SubTexture name="MISS GF Up0005" x="2174" y="1499" width="353" height="497"/>
	<SubTexture name="MISS GF Up0006" x="2174" y="1499" width="353" height="497"/>
	<SubTexture name="MISS GF Up0007" x="2174" y="1499" width="353" height="497"/>
	<SubTexture name="MISS GF Up0008" x="2174" y="1499" width="353" height="497"/>
	<SubTexture name="MISS GF Up0009" x="2174" y="1499" width="353" height="497"/>
	<SubTexture name="MISS GF Up0010" x="2174" y="1499" width="353" height="497"/>
	<SubTexture name="MISS GF Up0011" x="2174" y="1499" width="353" height="497"/>
	<SubTexture name="MISS GF Up0012" x="2174" y="1499" width="353" height="497"/>
	<SubTexture name="MISS GF Up0013" x="2174" y="1499" width="353" height="497"/>
	<SubTexture name="MISS GF Up0014" x="2174" y="1499" width="353" height="497"/>
</TextureAtlas>
